cv_pytorch/__init__.py
cv_pytorch/corners/__init__.py
cv_pytorch/corners/harris.py
cv_pytorch/feature_matching/__init__.py
cv_pytorch/feature_matching/sift.py
cv_pytorch/filters/__init__.py
cv_pytorch/filters/bilateral.py
cv_pytorch/filters/gaussian.py
cv_pytorch/filters/sharpen.py
cv_pytorch/filters/sobel.py
cv_pytorch/homography/__init__.py
cv_pytorch/homography/dlt.py
cv_pytorch/interpolation/__init__.py
cv_pytorch/interpolation/bilinear.py
cv_pytorch/interpolation/nearest_neighbor.py
cv_pytorch/lines/__init__.py
cv_pytorch/lines/hough.py
cv_pytorch/outliers/__init__.py
cv_pytorch/outliers/ransac.py
cv_pytorch/panorama/__init__.py
cv_pytorch/panorama/panorama.py
cv_pytorch/scale/__init__.py
cv_pytorch/scale/bilinear.py
cv_pytorch/scale/nearest_neighbor.py
cv_pytorch/utils/__init__.py
cv_pytorch/utils/difference.py
cv_pytorch/utils/figures.py
cv_pytorch/utils/runtime.py
cv_pytorch-0.0.8.dist-info/LICENSE
cv_pytorch-0.0.8.dist-info/METADATA
cv_pytorch-0.0.8.dist-info/WHEEL
cv_pytorch-0.0.8.dist-info/top_level.txt
cv_pytorch-0.0.8.dist-info/RECORD
