Metadata-Version: 2.1
Name: cv-pytorch
Version: 0.0.8
Summary: A collection of tools to help facilitate computer vision operations.
Author-email: Jorge Menjivar <jorgemenjivar1997@gmail.com>
Project-URL: Homepage, https://github.com/jorge-menjivar/CV-PyTorch
Project-URL: Bug Tracker, https://github.com/jorge-menjivar/CV-PyTorch/issues
Classifier: Programming Language :: Python :: 3
Classifier: License :: OSI Approved :: MIT License
Classifier: Operating System :: OS Independent
Requires-Python: >=3.7
License-File: LICENSE
Requires-Dist: matplotlib
Requires-Dist: numpy
Requires-Dist: scipy
Requires-Dist: scikit-image
Requires-Dist: torch (>=1.11.0)
Requires-Dist: torchvision (>=0.12.0)
